escape/__init__.py
pyescape-2019.10.16.8.31.59.29937.dist-info/LICENSE
pyescape-2019.10.16.8.31.59.29937.dist-info/METADATA
pyescape-2019.10.16.8.31.59.29937.dist-info/WHEEL
pyescape-2019.10.16.8.31.59.29937.dist-info/top_level.txt
pyescape-2019.10.16.8.31.59.29937.dist-info/RECORD
