Metadata-Version: 2.1
Name: pyescape
Version: 2019.10.16.8.31.59.29937
Summary: escape characters functions and utilities
Home-page: https://github.com/qaviton/escape
Author: yehonadav
Author-email: yonadav.barilan@gmail.com
License: apache-2.0
Platform: UNKNOWN
Classifier: Programming Language :: Python :: 3.7
